<?xml version="1.0" encoding="UTF-8"?>
<pardefs>
    <pardef n="o/ko__n">
      <e>
        <p>
          <l>ko</l>
          <r>ko<s n="n"/><s n="nt"/><s n="sg"/><s n="nom"/></r>
        </p>
      </e>
      <e>
        <p>
          <l>ka</l>
          <r>ko<s n="n"/><s n="nt"/><s n="sg"/><s n="gen"/></r>
        </p>
      </e>
      <e>
        <p>
          <l>ku</l>
          <r>ko<s n="n"/><s n="nt"/><s n="sg"/><s n="dat"/></r>
        </p>
      </e>
      <e>
        <p>
          <l>ko</l>
          <r>ko<s n="n"/><s n="nt"/><s n="sg"/><s n="acc"/></r>
        </p>
      </e>
      <e>
        <p>
          <l>kiem</l>
          <r>ko<s n="n"/><s n="nt"/><s n="sg"/><s n="ins"/></r>
        </p>
      </e>
      <e>
        <p>
          <l>ku</l>
          <r>ko<s n="n"/><s n="nt"/><s n="sg"/><s n="loc"/></r>
        </p>
      </e>
      <e>
        <p>
          <l>ko</l>
          <r>ko<s n="n"/><s n="nt"/><s n="sg"/><s n="voc"/></r>
        </p>
      </e>
      <e>
        <p>
          <l>czy</l>
          <r>ko<s n="n"/><s n="nt"/><s n="pl"/><s n="nom"/></r>
        </p>
      </e>
      <e r="LR">
        <p>
          <l>ka</l>
          <r>ko<s n="n"/><s n="nt"/><s n="pl"/><s n="nom"/></r>
        </p>
      </e>
      <e>
        <p>
          <l>czu</l>
          <r>ko<s n="n"/><s n="nt"/><s n="pl"/><s n="gen"/></r>
        </p>
      </e>
      <e r="LR">
        <p>
          <l>czów</l>
          <r>ko<s n="n"/><s n="nt"/><s n="pl"/><s n="gen"/></r>
        </p>
      </e>
      <e>
        <p>
          <l>czom</l>
          <r>ko<s n="n"/><s n="nt"/><s n="pl"/><s n="dat"/></r>
        </p>
      </e>
      <e>
        <p>
          <l>czy</l>
          <r>ko<s n="n"/><s n="nt"/><s n="pl"/><s n="acc"/></r>
        </p>
      </e>
      <e>
        <p>
          <l>czami</l>
          <r>ko<s n="n"/><s n="nt"/><s n="pl"/><s n="ins"/></r>
        </p>
      </e>
      <e r="LR">
        <p>
          <l>czyma</l>
          <r>ko<s n="n"/><s n="nt"/><s n="pl"/><s n="ins"/></r>
        </p>
      </e>
      <e>
        <p>
          <l>czach</l>
          <r>ko<s n="n"/><s n="nt"/><s n="pl"/><s n="loc"/></r>
        </p>
      </e>
      <e>
        <p>
          <l>czy</l>
          <r>ko<s n="n"/><s n="nt"/><s n="pl"/><s n="voc"/></r>
        </p>
      </e>
     </pardef>
    <pardef n="u/cho__n">
      <e>
        <p>
          <l>cho</l>
          <r>cho<s n="n"/><s n="nt"/><s n="sg"/><s n="nom"/></r>
        </p>
      </e>
      <e>
        <p>
          <l>cha</l>
          <r>cho<s n="n"/><s n="nt"/><s n="sg"/><s n="gen"/></r>
        </p>
      </e>
      <e>
        <p>
          <l>chu</l>
          <r>cho<s n="n"/><s n="nt"/><s n="sg"/><s n="dat"/></r>
        </p>
      </e>
      <e>
        <p>
          <l>cho</l>
          <r>cho<s n="n"/><s n="nt"/><s n="sg"/><s n="acc"/></r>
        </p>
      </e>
      <e>
        <p>
          <l>chem</l>
          <r>cho<s n="n"/><s n="nt"/><s n="sg"/><s n="ins"/></r>
        </p>
      </e>
      <e>
        <p>
          <l>chu</l>
          <r>cho<s n="n"/><s n="nt"/><s n="sg"/><s n="loc"/></r>
        </p>
      </e>
      <e>
        <p>
          <l>cho</l>
          <r>cho<s n="n"/><s n="nt"/><s n="sg"/><s n="voc"/></r>
        </p>
      </e>
      <e>
        <p>
          <l>szy</l>
          <r>cho<s n="n"/><s n="nt"/><s n="pl"/><s n="nom"/></r>
        </p>
      </e>
      <e r="LR">
        <p>
          <l>cha</l>
          <r>cho<s n="n"/><s n="nt"/><s n="pl"/><s n="nom"/></r>
        </p>
      </e>
      <e>
        <p>
          <l>szu</l>
          <r>cho<s n="n"/><s n="nt"/><s n="pl"/><s n="gen"/></r>
        </p>
      </e>
      <e r="LR">
        <p>
          <l>szów</l>
          <r>cho<s n="n"/><s n="nt"/><s n="pl"/><s n="gen"/></r>
        </p>
      </e>
      <e>
        <p>
          <l>szom</l>
          <r>cho<s n="n"/><s n="nt"/><s n="pl"/><s n="dat"/></r>
        </p>
      </e>
      <e>
        <p>
          <l>szy</l>
          <r>cho<s n="n"/><s n="nt"/><s n="pl"/><s n="acc"/></r>
        </p>
      </e>
      <e>
        <p>
          <l>szami</l>
          <r>cho<s n="n"/><s n="nt"/><s n="pl"/><s n="ins"/></r>
        </p>
      </e>
      <e r="LR">
        <p>
          <l>szyma</l>
          <r>cho<s n="n"/><s n="nt"/><s n="pl"/><s n="ins"/></r>
        </p>
      </e>
      <e>
        <p>
          <l>szach</l>
          <r>cho<s n="n"/><s n="nt"/><s n="pl"/><s n="loc"/></r>
        </p>
      </e>
      <e>
        <p>
          <l>szy</l>
          <r>cho<s n="n"/><s n="nt"/><s n="pl"/><s n="voc"/></r>
        </p>
      </e>
    </pardef>
    <pardef n="ok/no__n">
      <e>
        <p>
          <l>no</l>
          <r>no<s n="n"/><s n="nt"/><s n="sg"/><s n="nom"/></r>
        </p>
      </e>
      <e>
        <p>
          <l>na</l>
          <r>no<s n="n"/><s n="nt"/><s n="sg"/><s n="gen"/></r>
        </p>
      </e>
      <e>
        <p>
          <l>nu</l>
          <r>no<s n="n"/><s n="nt"/><s n="sg"/><s n="dat"/></r>
        </p>
      </e>
      <e>
        <p>
          <l>no</l>
          <r>no<s n="n"/><s n="nt"/><s n="sg"/><s n="acc"/></r>
        </p>
      </e>
      <e>
        <p>
          <l>num</l>
          <r>no<s n="n"/><s n="nt"/><s n="sg"/><s n="ins"/></r>
        </p>
      </e>
      <e>
        <p>
          <l>nie</l>
          <r>no<s n="n"/><s n="nt"/><s n="sg"/><s n="loc"/></r>
        </p>
      </e>
      <e>
        <p>
          <l>no</l>
          <r>no<s n="n"/><s n="nt"/><s n="sg"/><s n="voc"/></r>
        </p>
      </e>
      <e>
        <p>
          <l>na</l>
          <r>no<s n="n"/><s n="nt"/><s n="pl"/><s n="nom"/></r>
        </p>
      </e>
      <e>
        <p>
          <l>ien</l>
          <r>no<s n="n"/><s n="nt"/><s n="pl"/><s n="gen"/></r>
        </p>
      </e>
      <e>
        <p>
          <l>nom</l>
          <r>no<s n="n"/><s n="nt"/><s n="pl"/><s n="dat"/></r>
        </p>
      </e>
      <e>
        <p>
          <l>na</l>
          <r>no<s n="n"/><s n="nt"/><s n="pl"/><s n="acc"/></r>
        </p>
      </e>
      <e>
        <p>
          <l>nami</l>
          <r>no<s n="n"/><s n="nt"/><s n="pl"/><s n="ins"/></r>
        </p>
      </e>
      <e>
        <p>
          <l>nach</l>
          <r>no<s n="n"/><s n="nt"/><s n="pl"/><s n="loc"/></r>
        </p>
      </e>
      <e>
        <p>
          <l>na</l>
          <r>no<s n="n"/><s n="nt"/><s n="pl"/><s n="voc"/></r>
        </p>
      </e>
     </pardef>
    <pardef n="nas/ienie__n">
      <e>
        <p>
          <l>ienie</l>
          <r>ienie<s n="n"/><s n="nt"/><s n="sg"/><s n="nom"/></r>
        </p>
      </e>
      <e>
        <p>
          <l>ienia</l>
          <r>ienie<s n="n"/><s n="nt"/><s n="sg"/><s n="gen"/></r>
        </p>
      </e>
      <e>
        <p>
          <l>ieniu</l>
          <r>ienie<s n="n"/><s n="nt"/><s n="sg"/><s n="dat"/></r>
        </p>
      </e>
      <e>
        <p>
          <l>ienie</l>
          <r>ienie<s n="n"/><s n="nt"/><s n="sg"/><s n="acc"/></r>
        </p>
      </e>
      <e>
        <p>
          <l>ieniem</l>
          <r>ienie<s n="n"/><s n="nt"/><s n="sg"/><s n="ins"/></r>
        </p>
      </e>
      <e>
        <p>
          <l>ieniu</l>
          <r>ienie<s n="n"/><s n="nt"/><s n="sg"/><s n="loc"/></r>
        </p>
      </e>
      <e>
        <p>
          <l>ienie</l>
          <r>ienie<s n="n"/><s n="nt"/><s n="sg"/><s n="voc"/></r>
        </p>
      </e>
      <e>
        <p>
          <l>ionia</l>
          <r>ienie<s n="n"/><s n="nt"/><s n="pl"/><s n="nom"/></r>
        </p>
      </e>
      <e>
        <p>
          <l>ion</l>
          <r>ienie<s n="n"/><s n="nt"/><s n="pl"/><s n="gen"/></r>
        </p>
      </e>
      <e>
        <p>
          <l>ionom</l>
          <r>ienie<s n="n"/><s n="nt"/><s n="pl"/><s n="dat"/></r>
        </p>
      </e>
      <e>
        <p>
          <l>iona</l>
          <r>ienie<s n="n"/><s n="nt"/><s n="pl"/><s n="acc"/></r>
        </p>
      </e>
      <e>
        <p>
          <l>ionami</l>
          <r>ienie<s n="n"/><s n="nt"/><s n="pl"/><s n="ins"/></r>
        </p>
      </e>
      <e>
        <p>
          <l>ionach</l>
          <r>ienie<s n="n"/><s n="nt"/><s n="pl"/><s n="loc"/></r>
        </p>
      </e>
      <e>
        <p>
          <l>iona</l>
          <r>ienie<s n="n"/><s n="nt"/><s n="pl"/><s n="voc"/></r>
        </p>
      </e>
    </pardef>
    <pardef n="m/orze__n">
      <e>
        <p>
          <l>orze</l>
          <r>orze<s n="n"/><s n="nt"/><s n="sg"/><s n="nom"/></r>
        </p>
      </e>
      <e>
        <p>
          <l>orza</l>
          <r>orze<s n="n"/><s n="nt"/><s n="sg"/><s n="gen"/></r>
        </p>
      </e>
      <e>
        <p>
          <l>orzu</l>
          <r>orze<s n="n"/><s n="nt"/><s n="sg"/><s n="dat"/></r>
        </p>
      </e>
      <e>
        <p>
          <l>orze</l>
          <r>orze<s n="n"/><s n="nt"/><s n="sg"/><s n="acc"/></r>
        </p>
      </e>
      <e>
        <p>
          <l>orzem</l>
          <r>orze<s n="n"/><s n="nt"/><s n="sg"/><s n="ins"/></r>
        </p>
      </e>
      <e>
        <p>
          <l>orzu</l>
          <r>orze<s n="n"/><s n="nt"/><s n="sg"/><s n="loc"/></r>
        </p>
      </e>
      <e>
        <p>
          <l>orze</l>
          <r>orze<s n="n"/><s n="nt"/><s n="sg"/><s n="voc"/></r>
        </p>
      </e>
      <e>
        <p>
          <l>orza</l>
          <r>orze<s n="n"/><s n="nt"/><s n="pl"/><s n="nom"/></r>
        </p>
      </e>
      <e>
        <p>
          <l>órz</l>
          <r>orze<s n="n"/><s n="nt"/><s n="pl"/><s n="gen"/></r>
        </p>
      </e>
      <e>
        <p>
          <l>orzom</l>
          <r>orze<s n="n"/><s n="nt"/><s n="pl"/><s n="dat"/></r>
        </p>
      </e>
      <e>
        <p>
          <l>orza</l>
          <r>orze<s n="n"/><s n="nt"/><s n="pl"/><s n="acc"/></r>
        </p>
      </e>
      <e>
        <p>
          <l>orzami</l>
          <r>orze<s n="n"/><s n="nt"/><s n="pl"/><s n="ins"/></r>
        </p>
      </e>
      <e>
        <p>
          <l>orzach</l>
          <r>orze<s n="n"/><s n="nt"/><s n="pl"/><s n="loc"/></r>
        </p>
      </e>
      <e>
        <p>
          <l>orza</l>
          <r>orze<s n="n"/><s n="nt"/><s n="pl"/><s n="voc"/></r>
        </p>
      </e>
    </pardef>
    <pardef n="p/ole__n">
      <e>
        <p>
          <l>ole</l>
          <r>ole<s n="n"/><s n="nt"/><s n="sg"/><s n="nom"/></r>
        </p>
      </e>
      <e>
        <p>
          <l>ola</l>
          <r>ole<s n="n"/><s n="nt"/><s n="sg"/><s n="gen"/></r>
        </p>
      </e>
      <e>
        <p>
          <l>olu</l>
          <r>ole<s n="n"/><s n="nt"/><s n="sg"/><s n="dat"/></r>
        </p>
      </e>
      <e>
        <p>
          <l>ole</l>
          <r>ole<s n="n"/><s n="nt"/><s n="sg"/><s n="acc"/></r>
        </p>
      </e>
      <e>
        <p>
          <l>olem</l>
          <r>ole<s n="n"/><s n="nt"/><s n="sg"/><s n="ins"/></r>
        </p>
      </e>
      <e>
        <p>
          <l>olu</l>
          <r>ole<s n="n"/><s n="nt"/><s n="sg"/><s n="loc"/></r>
        </p>
      </e>
      <e>
        <p>
          <l>ole</l>
          <r>ole<s n="n"/><s n="nt"/><s n="sg"/><s n="voc"/></r>
        </p>
      </e>
      <e>
        <p>
          <l>ola</l>
          <r>ole<s n="n"/><s n="nt"/><s n="pl"/><s n="nom"/></r>
        </p>
      </e>
      <e>
        <p>
          <l>ól</l>
          <r>ole<s n="n"/><s n="nt"/><s n="pl"/><s n="gen"/></r>
        </p>
      </e>
      <e>
        <p>
          <l>olom</l>
          <r>ole<s n="n"/><s n="nt"/><s n="pl"/><s n="dat"/></r>
        </p>
      </e>
      <e>
        <p>
          <l>ola</l>
          <r>ole<s n="n"/><s n="nt"/><s n="pl"/><s n="acc"/></r>
        </p>
      </e>
      <e>
        <p>
          <l>olami</l>
          <r>ole<s n="n"/><s n="nt"/><s n="pl"/><s n="ins"/></r>
        </p>
      </e>
      <e>
        <p>
          <l>olach</l>
          <r>ole<s n="n"/><s n="nt"/><s n="pl"/><s n="loc"/></r>
        </p>
      </e>
      <e>
        <p>
          <l>ola</l>
          <r>ole<s n="n"/><s n="nt"/><s n="pl"/><s n="voc"/></r>
        </p>
      </e>
    </pardef>
    <pardef n="ud/o__n">
      <e>
        <p>
          <l>o</l>
          <r>o<s n="n"/><s n="nt"/><s n="sg"/><s n="nom"/></r>
        </p>
      </e>
      <e>
        <p>
          <l>a</l>
          <r>o<s n="n"/><s n="nt"/><s n="sg"/><s n="gen"/></r>
        </p>
      </e>
      <e>
        <p>
          <l>u</l>
          <r>o<s n="n"/><s n="nt"/><s n="sg"/><s n="dat"/></r>
        </p>
      </e>
      <e>
        <p>
          <l>o</l>
          <r>o<s n="n"/><s n="nt"/><s n="sg"/><s n="acc"/></r>
        </p>
      </e>
      <e>
        <p>
          <l>em</l>
          <r>o<s n="n"/><s n="nt"/><s n="sg"/><s n="ins"/></r>
        </p>
      </e>
      <e>
        <p>
          <l>zie</l>
          <r>o<s n="n"/><s n="nt"/><s n="sg"/><s n="loc"/></r>
        </p>
      </e>
      <e>
        <p>
          <l>o</l>
          <r>o<s n="n"/><s n="nt"/><s n="sg"/><s n="voc"/></r>
        </p>
      </e>
      <e>
        <p>
          <l>a</l>
          <r>o<s n="n"/><s n="nt"/><s n="pl"/><s n="nom"/></r>
        </p>
      </e>
      <e>
        <p>
          <l></l>
          <r>o<s n="n"/><s n="nt"/><s n="pl"/><s n="gen"/></r>
        </p>
      </e>
      <e>
        <p>
          <l>om</l>
          <r>o<s n="n"/><s n="nt"/><s n="pl"/><s n="dat"/></r>
        </p>
      </e>
      <e>
        <p>
          <l>a</l>
          <r>o<s n="n"/><s n="nt"/><s n="pl"/><s n="acc"/></r>
        </p>
      </e>
      <e>
        <p>
          <l>ami</l>
          <r>o<s n="n"/><s n="nt"/><s n="pl"/><s n="ins"/></r>
        </p>
      </e>
      <e>
        <p>
          <l>ach</l>
          <r>o<s n="n"/><s n="nt"/><s n="pl"/><s n="loc"/></r>
        </p>
      </e>
      <e>
        <p>
          <l>a</l>
          <r>o<s n="n"/><s n="nt"/><s n="pl"/><s n="voc"/></r>
        </p>
      </e>
    </pardef>
    <pardef n="zer/o__n">
      <e>
        <p>
          <l>o</l>
          <r>o<s n="n"/><s n="nt"/><s n="sg"/><s n="nom"/></r>
        </p>
      </e>
      <e>
        <p>
          <l>a</l>
          <r>o<s n="n"/><s n="nt"/><s n="sg"/><s n="gen"/></r>
        </p>
      </e>
      <e>
        <p>
          <l>u</l>
          <r>o<s n="n"/><s n="nt"/><s n="sg"/><s n="dat"/></r>
        </p>
      </e>
      <e>
        <p>
          <l>o</l>
          <r>o<s n="n"/><s n="nt"/><s n="sg"/><s n="acc"/></r>
        </p>
      </e>
      <e>
        <p>
          <l>em</l>
          <r>o<s n="n"/><s n="nt"/><s n="sg"/><s n="ins"/></r>
        </p>
      </e>
      <e>
        <p>
          <l>ze</l>
          <r>o<s n="n"/><s n="nt"/><s n="sg"/><s n="loc"/></r>
        </p>
      </e>
      <e>
        <p>
          <l>o</l>
          <r>o<s n="n"/><s n="nt"/><s n="sg"/><s n="voc"/></r>
        </p>
      </e>
      <e>
        <p>
          <l>a</l>
          <r>o<s n="n"/><s n="nt"/><s n="pl"/><s n="nom"/></r>
        </p>
      </e>
      <e>
        <p>
          <l></l>
          <r>o<s n="n"/><s n="nt"/><s n="pl"/><s n="gen"/></r>
        </p>
      </e>
      <e>
        <p>
          <l>om</l>
          <r>o<s n="n"/><s n="nt"/><s n="pl"/><s n="dat"/></r>
        </p>
      </e>
      <e>
        <p>
          <l>a</l>
          <r>o<s n="n"/><s n="nt"/><s n="pl"/><s n="acc"/></r>
        </p>
      </e>
      <e>
        <p>
          <l>ami</l>
          <r>o<s n="n"/><s n="nt"/><s n="pl"/><s n="ins"/></r>
        </p>
      </e>
      <e>
        <p>
          <l>ach</l>
          <r>o<s n="n"/><s n="nt"/><s n="pl"/><s n="loc"/></r>
        </p>
      </e>
      <e>
        <p>
          <l>a</l>
          <r>o<s n="n"/><s n="nt"/><s n="pl"/><s n="voc"/></r>
        </p>
      </e>
    </pardef>
    <pardef n="nieb/o__n">
      <e>
        <p>
          <l>o</l>
          <r>o<s n="n"/><s n="nt"/><s n="sg"/><s n="nom"/></r>
        </p>
      </e>
      <e>
        <p>
          <l>a</l>
          <r>o<s n="n"/><s n="nt"/><s n="sg"/><s n="gen"/></r>
        </p>
      </e>
      <e>
        <p>
          <l>u</l>
          <r>o<s n="n"/><s n="nt"/><s n="sg"/><s n="dat"/></r>
        </p>
      </e>
      <e>
        <p>
          <l>o</l>
          <r>o<s n="n"/><s n="nt"/><s n="sg"/><s n="acc"/></r>
        </p>
      </e>
      <e>
        <p>
          <l>em</l>
          <r>o<s n="n"/><s n="nt"/><s n="sg"/><s n="ins"/></r>
        </p>
      </e>
      <e>
        <p>
          <l>ie</l>
          <r>o<s n="n"/><s n="nt"/><s n="sg"/><s n="loc"/></r>
        </p>
      </e>
      <e>
        <p>
          <l>o</l>
          <r>o<s n="n"/><s n="nt"/><s n="sg"/><s n="voc"/></r>
        </p>
      </e>
      <e>
        <p>
          <l>iosa</l>
          <r>o<s n="n"/><s n="nt"/><s n="pl"/><s n="nom"/></r>
        </p>
      </e>
      <e r="LR">
        <p>
          <l>a</l>
          <r>o<s n="n"/><s n="nt"/><s n="pl"/><s n="nom"/></r>
        </p>
      </e>
      <e>
        <p>
          <l>ios</l>
          <r>o<s n="n"/><s n="nt"/><s n="pl"/><s n="gen"/></r>
        </p>
      </e>
      <e>
        <p>
          <l>iosom</l>
          <r>o<s n="n"/><s n="nt"/><s n="pl"/><s n="dat"/></r>
        </p>
      </e>
      <e>
        <p>
          <l>iosa</l>
          <r>o<s n="n"/><s n="nt"/><s n="pl"/><s n="acc"/></r>
        </p>
      </e>
      <e r="LR">
        <p>
          <l>a</l>
          <r>o<s n="n"/><s n="nt"/><s n="pl"/><s n="acc"/></r>
        </p>
      </e>
      <e>
        <p>
          <l>iosami</l>
          <r>o<s n="n"/><s n="nt"/><s n="pl"/><s n="ins"/></r>
        </p>
      </e>
      <e>
        <p>
          <l>iosach</l>
          <r>o<s n="n"/><s n="nt"/><s n="pl"/><s n="loc"/></r>
        </p>
      </e>
      <e>
        <p>
          <l>iosa</l>
          <r>o<s n="n"/><s n="nt"/><s n="pl"/><s n="voc"/></r>
        </p>
      </e>
      <e r="LR">
        <p>
          <l>a</l>
          <r>o<s n="n"/><s n="nt"/><s n="pl"/><s n="voc"/></r>
        </p>
      </e>
    </pardef>
    <pardef n="d/no__n">
      <e>
        <p>
          <l>no</l>
          <r>no<s n="n"/><s n="nt"/><s n="sg"/><s n="nom"/></r>
        </p>
      </e>
      <e>
        <p>
          <l>na</l>
          <r>no<s n="n"/><s n="nt"/><s n="sg"/><s n="gen"/></r>
        </p>
      </e>
      <e>
        <p>
          <l>nu</l>
          <r>no<s n="n"/><s n="nt"/><s n="sg"/><s n="dat"/></r>
        </p>
      </e>
      <e>
        <p>
          <l>no</l>
          <r>no<s n="n"/><s n="nt"/><s n="sg"/><s n="acc"/></r>
        </p>
      </e>
      <e>
        <p>
          <l>nem</l>
          <r>no<s n="n"/><s n="nt"/><s n="sg"/><s n="ins"/></r>
        </p>
      </e>
      <e>
        <p>
          <l>nie</l>
          <r>no<s n="n"/><s n="nt"/><s n="sg"/><s n="loc"/></r>
        </p>
      </e>
      <e>
        <p>
          <l>no</l>
          <r>no<s n="n"/><s n="nt"/><s n="sg"/><s n="voc"/></r>
        </p>
      </e>
      <e>
        <p>
          <l>na</l>
          <r>no<s n="n"/><s n="nt"/><s n="pl"/><s n="nom"/></r>
        </p>
      </e>
      <e>
        <p>
          <l>en</l>
          <r>no<s n="n"/><s n="nt"/><s n="pl"/><s n="gen"/></r>
        </p>
      </e>
      <e>
        <p>
          <l>nom</l>
          <r>no<s n="n"/><s n="nt"/><s n="pl"/><s n="dat"/></r>
        </p>
      </e>
      <e>
        <p>
          <l>na</l>
          <r>no<s n="n"/><s n="nt"/><s n="pl"/><s n="acc"/></r>
        </p>
      </e>
      <e>
        <p>
          <l>nami</l>
          <r>no<s n="n"/><s n="nt"/><s n="pl"/><s n="ins"/></r>
        </p>
      </e>
      <e>
        <p>
          <l>nach</l>
          <r>no<s n="n"/><s n="nt"/><s n="pl"/><s n="loc"/></r>
        </p>
      </e>
      <e>
        <p>
          <l>na</l>
          <r>no<s n="n"/><s n="nt"/><s n="pl"/><s n="voc"/></r>
        </p>
      </e>
    </pardef>
    <pardef n="gwi/azdo__n">
      <e>
        <p>
          <l>azdo</l>
          <r>azdo<s n="n"/><s n="nt"/><s n="sg"/><s n="nom"/></r>
        </p>
      </e>
      <e>
        <p>
          <l>azda</l>
          <r>azdo<s n="n"/><s n="nt"/><s n="sg"/><s n="gen"/></r>
        </p>
      </e>
      <e>
        <p>
          <l>azdu</l>
          <r>azdo<s n="n"/><s n="nt"/><s n="sg"/><s n="dat"/></r>
        </p>
      </e>
      <e>
        <p>
          <l>azdo</l>
          <r>azdo<s n="n"/><s n="nt"/><s n="sg"/><s n="acc"/></r>
        </p>
      </e>
      <e>
        <p>
          <l>azdem</l>
          <r>azdo<s n="n"/><s n="nt"/><s n="sg"/><s n="ins"/></r>
        </p>
      </e>
      <e>
        <p>
          <l>eździe</l>
          <r>azdo<s n="n"/><s n="nt"/><s n="sg"/><s n="loc"/></r>
        </p>
      </e>
      <e>
        <p>
          <l>azdo</l>
          <r>azdo<s n="n"/><s n="nt"/><s n="sg"/><s n="voc"/></r>
        </p>
      </e>
      <e>
        <p>
          <l>azda</l>
          <r>azdo<s n="n"/><s n="nt"/><s n="pl"/><s n="nom"/></r>
        </p>
      </e>
      <e>
        <p>
          <l>azd</l>
          <r>azdo<s n="n"/><s n="nt"/><s n="pl"/><s n="gen"/></r>
        </p>
      </e>
      <e>
        <p>
          <l>azdom</l>
          <r>azdo<s n="n"/><s n="nt"/><s n="pl"/><s n="dat"/></r>
        </p>
      </e>
      <e>
        <p>
          <l>azdo</l>
          <r>azdo<s n="n"/><s n="nt"/><s n="pl"/><s n="acc"/></r>
        </p>
      </e>
      <e>
        <p>
          <l>azdami</l>
          <r>azdo<s n="n"/><s n="nt"/><s n="pl"/><s n="ins"/></r>
        </p>
      </e>
      <e>
        <p>
          <l>azdach</l>
          <r>azdo<s n="n"/><s n="nt"/><s n="pl"/><s n="loc"/></r>
        </p>
      </e>
      <e>
        <p>
          <l>azda</l>
          <r>azdo<s n="n"/><s n="nt"/><s n="pl"/><s n="voc"/></r>
        </p>
      </e>
    </pardef>
    <pardef n="t/ło__n">
      <e>
        <p>
          <l>ło</l>
          <r>ło<s n="n"/><s n="nt"/><s n="sg"/><s n="nom"/></r>
        </p>
      </e>
      <e>
        <p>
          <l>ła</l>
          <r>ło<s n="n"/><s n="nt"/><s n="sg"/><s n="gen"/></r>
        </p>
      </e>
      <e>
        <p>
          <l>łu</l>
          <r>ło<s n="n"/><s n="nt"/><s n="sg"/><s n="dat"/></r>
        </p>
      </e>
      <e>
        <p>
          <l>ło</l>
          <r>ło<s n="n"/><s n="nt"/><s n="sg"/><s n="acc"/></r>
        </p>
      </e>
      <e>
        <p>
          <l>łem</l>
          <r>ło<s n="n"/><s n="nt"/><s n="sg"/><s n="ins"/></r>
        </p>
      </e>
      <e>
        <p>
          <l>le</l>
          <r>ło<s n="n"/><s n="nt"/><s n="sg"/><s n="loc"/></r>
        </p>
      </e>
      <e>
        <p>
          <l>ło</l>
          <r>ło<s n="n"/><s n="nt"/><s n="sg"/><s n="voc"/></r>
        </p>
      </e>
      <e>
        <p>
          <l>ła</l>
          <r>ło<s n="n"/><s n="nt"/><s n="pl"/><s n="nom"/></r>
        </p>
      </e>
      <e>
        <p>
          <l>eł</l>
          <r>ło<s n="n"/><s n="nt"/><s n="pl"/><s n="gen"/></r>
        </p>
      </e>
      <e>
        <p>
          <l>łom</l>
          <r>ło<s n="n"/><s n="nt"/><s n="pl"/><s n="dat"/></r>
        </p>
      </e>
      <e>
        <p>
          <l>ła</l>
          <r>ło<s n="n"/><s n="nt"/><s n="pl"/><s n="acc"/></r>
        </p>
      </e>
      <e>
        <p>
          <l>łami</l>
          <r>ło<s n="n"/><s n="nt"/><s n="pl"/><s n="ins"/></r>
        </p>
      </e>
      <e>
        <p>
          <l>łach</l>
          <r>ło<s n="n"/><s n="nt"/><s n="pl"/><s n="loc"/></r>
        </p>
      </e>
      <e>
        <p>
          <l>ła</l>
          <r>ło<s n="n"/><s n="nt"/><s n="pl"/><s n="voc"/></r>
        </p>
      </e>
    </pardef>
    <pardef n="z/ło__n">
      <e>
        <p>
          <l>ło</l>
          <r>ło<s n="n"/><s n="nt"/><s n="sg"/><s n="nom"/></r>
        </p>
      </e>
      <e>
        <p>
          <l>ła</l>
          <r>ło<s n="n"/><s n="nt"/><s n="sg"/><s n="gen"/></r>
        </p>
      </e>
      <e>
        <p>
          <l>łu</l>
          <r>ło<s n="n"/><s n="nt"/><s n="sg"/><s n="dat"/></r>
        </p>
      </e>
      <e>
        <p>
          <l>ło</l>
          <r>ło<s n="n"/><s n="nt"/><s n="sg"/><s n="acc"/></r>
        </p>
      </e>
      <e>
        <p>
          <l>łem</l>
          <r>ło<s n="n"/><s n="nt"/><s n="sg"/><s n="ins"/></r>
        </p>
      </e>
      <e>
        <p>
          <l>łu</l>
          <r>ło<s n="n"/><s n="nt"/><s n="sg"/><s n="loc"/></r>
        </p>
      </e>
      <e>
        <p>
          <l>ło</l>
          <r>ło<s n="n"/><s n="nt"/><s n="sg"/><s n="voc"/></r>
        </p>
      </e>
      <e>
        <p>
          <l>ła</l>
          <r>ło<s n="n"/><s n="nt"/><s n="pl"/><s n="nom"/></r>
        </p>
      </e>
      <e>
        <p>
          <l>eł</l>
          <r>ło<s n="n"/><s n="nt"/><s n="pl"/><s n="gen"/></r>
        </p>
      </e>
      <e>
        <p>
          <l>łom</l>
          <r>ło<s n="n"/><s n="nt"/><s n="pl"/><s n="dat"/></r>
        </p>
      </e>
      <e>
        <p>
          <l>ła</l>
          <r>ło<s n="n"/><s n="nt"/><s n="pl"/><s n="acc"/></r>
        </p>
      </e>
      <e>
        <p>
          <l>łami</l>
          <r>ło<s n="n"/><s n="nt"/><s n="pl"/><s n="ins"/></r>
        </p>
      </e>
      <e>
        <p>
          <l>łach</l>
          <r>ło<s n="n"/><s n="nt"/><s n="pl"/><s n="loc"/></r>
        </p>
      </e>
      <e>
        <p>
          <l>ła</l>
          <r>ło<s n="n"/><s n="nt"/><s n="pl"/><s n="voc"/></r>
        </p>
      </e>
    </pardef>
    <pardef n="d/obro__n">
      <e>
        <p>
          <l>obro</l>
          <r>obro<s n="n"/><s n="nt"/><s n="sg"/><s n="nom"/></r>
        </p>
      </e>
      <e>
        <p>
          <l>obra</l>
          <r>obro<s n="n"/><s n="nt"/><s n="sg"/><s n="gen"/></r>
        </p>
      </e>
      <e>
        <p>
          <l>obru</l>
          <r>obro<s n="n"/><s n="nt"/><s n="sg"/><s n="dat"/></r>
        </p>
      </e>
      <e>
        <p>
          <l>obro</l>
          <r>obro<s n="n"/><s n="nt"/><s n="sg"/><s n="acc"/></r>
        </p>
      </e>
      <e>
        <p>
          <l>obrem</l>
          <r>obro<s n="n"/><s n="nt"/><s n="sg"/><s n="ins"/></r>
        </p>
      </e>
      <e>
        <p>
          <l>obru</l>
          <r>obro<s n="n"/><s n="nt"/><s n="sg"/><s n="loc"/></r>
        </p>
      </e>
      <e>
        <p>
          <l>obro</l>
          <r>obro<s n="n"/><s n="nt"/><s n="sg"/><s n="voc"/></r>
        </p>
      </e>
      <e>
        <p>
          <l>obra</l>
          <r>obro<s n="n"/><s n="nt"/><s n="pl"/><s n="nom"/></r>
        </p>
      </e>
      <e>
        <p>
          <l>óbr</l>
          <r>obro<s n="n"/><s n="nt"/><s n="pl"/><s n="gen"/></r>
        </p>
      </e>
      <e>
        <p>
          <l>obrom</l>
          <r>obro<s n="n"/><s n="nt"/><s n="pl"/><s n="dat"/></r>
        </p>
      </e>
      <e>
        <p>
          <l>obra</l>
          <r>obro<s n="n"/><s n="nt"/><s n="pl"/><s n="acc"/></r>
        </p>
      </e>
      <e>
        <p>
          <l>obrami</l>
          <r>obro<s n="n"/><s n="nt"/><s n="pl"/><s n="ins"/></r>
        </p>
      </e>
      <e>
        <p>
          <l>obrach</l>
          <r>obro<s n="n"/><s n="nt"/><s n="pl"/><s n="loc"/></r>
        </p>
      </e>
      <e>
        <p>
          <l>obra</l>
          <r>obro<s n="n"/><s n="nt"/><s n="pl"/><s n="voc"/></r>
        </p>
      </e>
    </pardef>
    <pardef n="wojsk/o__n">
      <e>
        <p>
          <l>o</l>
          <r>o<s n="n"/><s n="nt"/><s n="sg"/><s n="nom"/></r>
        </p>
      </e>
      <e>
        <p>
          <l>a</l>
          <r>o<s n="n"/><s n="nt"/><s n="sg"/><s n="gen"/></r>
        </p>
      </e>
      <e>
        <p>
          <l>u</l>
          <r>o<s n="n"/><s n="nt"/><s n="sg"/><s n="dat"/></r>
        </p>
      </e>
      <e>
        <p>
          <l>o</l>
          <r>o<s n="n"/><s n="nt"/><s n="sg"/><s n="acc"/></r>
        </p>
      </e>
      <e>
        <p>
          <l>iem</l>
          <r>o<s n="n"/><s n="nt"/><s n="sg"/><s n="ins"/></r>
        </p>
      </e>
      <e>
        <p>
          <l>u</l>
          <r>o<s n="n"/><s n="nt"/><s n="sg"/><s n="loc"/></r>
        </p>
      </e>
      <e>
        <p>
          <l>o</l>
          <r>o<s n="n"/><s n="nt"/><s n="sg"/><s n="voc"/></r>
        </p>
      </e>
      <e>
        <p>
          <l>a</l>
          <r>o<s n="n"/><s n="nt"/><s n="pl"/><s n="nom"/></r>
        </p>
      </e>
      <e>
        <p>
          <l></l>
          <r>o<s n="n"/><s n="nt"/><s n="pl"/><s n="gen"/></r>
        </p>
      </e>
      <e>
        <p>
          <l>om</l>
          <r>o<s n="n"/><s n="nt"/><s n="pl"/><s n="dat"/></r>
        </p>
      </e>
      <e>
        <p>
          <l>a</l>
          <r>o<s n="n"/><s n="nt"/><s n="pl"/><s n="acc"/></r>
        </p>
      </e>
      <e>
        <p>
          <l>ami</l>
          <r>o<s n="n"/><s n="nt"/><s n="pl"/><s n="ins"/></r>
        </p>
      </e>
      <e>
        <p>
          <l>ach</l>
          <r>o<s n="n"/><s n="nt"/><s n="pl"/><s n="loc"/></r>
        </p>
      </e>
      <e>
        <p>
          <l>a</l>
          <r>o<s n="n"/><s n="nt"/><s n="pl"/><s n="voc"/></r>
        </p>
      </e>
    </pardef>
    <pardef n="ech/o__n">
      <e>
        <p>
          <l>o</l>
          <r>o<s n="n"/><s n="nt"/><s n="sg"/><s n="nom"/></r>
        </p>
      </e>
      <e>
        <p>
          <l>a</l>
          <r>o<s n="n"/><s n="nt"/><s n="sg"/><s n="gen"/></r>
        </p>
      </e>
      <e>
        <p>
          <l>u</l>
          <r>o<s n="n"/><s n="nt"/><s n="sg"/><s n="dat"/></r>
        </p>
      </e>
      <e>
        <p>
          <l>o</l>
          <r>o<s n="n"/><s n="nt"/><s n="sg"/><s n="acc"/></r>
        </p>
      </e>
      <e>
        <p>
          <l>em</l>
          <r>o<s n="n"/><s n="nt"/><s n="sg"/><s n="ins"/></r>
        </p>
      </e>
      <e>
        <p>
          <l>u</l>
          <r>o<s n="n"/><s n="nt"/><s n="sg"/><s n="loc"/></r>
        </p>
      </e>
      <e>
        <p>
          <l>o</l>
          <r>o<s n="n"/><s n="nt"/><s n="sg"/><s n="voc"/></r>
        </p>
      </e>
      <e>
        <p>
          <l>a</l>
          <r>o<s n="n"/><s n="nt"/><s n="pl"/><s n="nom"/></r>
        </p>
      </e>
      <e>
        <p>
          <l></l>
          <r>o<s n="n"/><s n="nt"/><s n="pl"/><s n="gen"/></r>
        </p>
      </e>
      <e>
        <p>
          <l>om</l>
          <r>o<s n="n"/><s n="nt"/><s n="pl"/><s n="dat"/></r>
        </p>
      </e>
      <e>
        <p>
          <l>a</l>
          <r>o<s n="n"/><s n="nt"/><s n="pl"/><s n="acc"/></r>
        </p>
      </e>
      <e>
        <p>
          <l>ami</l>
          <r>o<s n="n"/><s n="nt"/><s n="pl"/><s n="ins"/></r>
        </p>
      </e>
      <e>
        <p>
          <l>ach</l>
          <r>o<s n="n"/><s n="nt"/><s n="pl"/><s n="loc"/></r>
        </p>
      </e>
      <e>
        <p>
          <l>a</l>
          <r>o<s n="n"/><s n="nt"/><s n="pl"/><s n="voc"/></r>
        </p>
      </e>
    </pardef>
    <pardef n="chłopisk/o__n">
      <e>
        <p>
          <l>o</l>
          <r>o<s n="n"/><s n="nt"/><s n="sg"/><s n="nom"/></r>
        </p>
      </e>
      <e>
        <p>
          <l>a</l>
          <r>o<s n="n"/><s n="nt"/><s n="sg"/><s n="gen"/></r>
        </p>
      </e>
      <e>
        <p>
          <l>u</l>
          <r>o<s n="n"/><s n="nt"/><s n="sg"/><s n="dat"/></r>
        </p>
      </e>
      <e>
        <p>
          <l>o</l>
          <r>o<s n="n"/><s n="nt"/><s n="sg"/><s n="acc"/></r>
        </p>
      </e>
      <e>
        <p>
          <l>iem</l>
          <r>o<s n="n"/><s n="nt"/><s n="sg"/><s n="ins"/></r>
        </p>
      </e>
      <e>
        <p>
          <l>u</l>
          <r>o<s n="n"/><s n="nt"/><s n="sg"/><s n="loc"/></r>
        </p>
      </e>
      <e>
        <p>
          <l>o</l>
          <r>o<s n="n"/><s n="nt"/><s n="sg"/><s n="voc"/></r>
        </p>
      </e>
      <e>
        <p>
          <l>a</l>
          <r>o<s n="n"/><s n="nt"/><s n="pl"/><s n="nom"/></r>
        </p>
      </e>
      <e>
        <p>
          <l>ów</l>
          <r>o<s n="n"/><s n="nt"/><s n="pl"/><s n="gen"/></r>
        </p>
      </e>
      <e>
        <p>
          <l>om</l>
          <r>o<s n="n"/><s n="nt"/><s n="pl"/><s n="dat"/></r>
        </p>
      </e>
      <e>
        <p>
          <l>a</l>
          <r>o<s n="n"/><s n="nt"/><s n="pl"/><s n="acc"/></r>
        </p>
      </e>
      <e>
        <p>
          <l>ami</l>
          <r>o<s n="n"/><s n="nt"/><s n="pl"/><s n="ins"/></r>
        </p>
      </e>
      <e>
        <p>
          <l>ach</l>
          <r>o<s n="n"/><s n="nt"/><s n="pl"/><s n="loc"/></r>
        </p>
      </e>
      <e>
        <p>
          <l>a</l>
          <r>o<s n="n"/><s n="nt"/><s n="pl"/><s n="voc"/></r>
        </p>
      </e>
    </pardef>
    <pardef n="pysi/o__n">
      <e>
        <p>
          <l>o</l>
          <r>o<s n="n"/><s n="nt"/><s n="sg"/><s n="nom"/></r>
        </p>
      </e>
      <e>
        <p>
          <l>a</l>
          <r>o<s n="n"/><s n="nt"/><s n="sg"/><s n="gen"/></r>
        </p>
      </e>
      <e>
        <p>
          <l>u</l>
          <r>o<s n="n"/><s n="nt"/><s n="sg"/><s n="dat"/></r>
        </p>
      </e>
      <e>
        <p>
          <l>o</l>
          <r>o<s n="n"/><s n="nt"/><s n="sg"/><s n="acc"/></r>
        </p>
      </e>
      <e>
        <p>
          <l>em</l>
          <r>o<s n="n"/><s n="nt"/><s n="sg"/><s n="ins"/></r>
        </p>
      </e>
      <e>
        <p>
          <l>u</l>
          <r>o<s n="n"/><s n="nt"/><s n="sg"/><s n="loc"/></r>
        </p>
      </e>
      <e>
        <p>
          <l>o</l>
          <r>o<s n="n"/><s n="nt"/><s n="sg"/><s n="voc"/></r>
        </p>
      </e>
      <e>
        <p>
          <l>a</l>
          <r>o<s n="n"/><s n="nt"/><s n="pl"/><s n="nom"/></r>
        </p>
      </e>
      <e>
        <p>
          <l>ów</l>
          <r>o<s n="n"/><s n="nt"/><s n="pl"/><s n="gen"/></r>
        </p>
      </e>
      <e>
        <p>
          <l>om</l>
          <r>o<s n="n"/><s n="nt"/><s n="pl"/><s n="dat"/></r>
        </p>
      </e>
      <e>
        <p>
          <l>a</l>
          <r>o<s n="n"/><s n="nt"/><s n="pl"/><s n="acc"/></r>
        </p>
      </e>
      <e>
        <p>
          <l>ami</l>
          <r>o<s n="n"/><s n="nt"/><s n="pl"/><s n="ins"/></r>
        </p>
      </e>
      <e>
        <p>
          <l>ach</l>
          <r>o<s n="n"/><s n="nt"/><s n="pl"/><s n="loc"/></r>
        </p>
      </e>
      <e>
        <p>
          <l>a</l>
          <r>o<s n="n"/><s n="nt"/><s n="pl"/><s n="voc"/></r>
        </p>
      </e>
    </pardef>
    <pardef n="cud/o__n">
      <e>
        <p>
          <l>o</l>
          <r>o<s n="n"/><s n="nt"/><s n="sg"/><s n="nom"/></r>
        </p>
      </e>
      <e>
        <p>
          <l>a</l>
          <r>o<s n="n"/><s n="nt"/><s n="sg"/><s n="gen"/></r>
        </p>
      </e>
      <e>
        <p>
          <l>u</l>
          <r>o<s n="n"/><s n="nt"/><s n="sg"/><s n="dat"/></r>
        </p>
      </e>
      <e>
        <p>
          <l>o</l>
          <r>o<s n="n"/><s n="nt"/><s n="sg"/><s n="acc"/></r>
        </p>
      </e>
      <e>
        <p>
          <l>em</l>
          <r>o<s n="n"/><s n="nt"/><s n="sg"/><s n="ins"/></r>
        </p>
      </e>
      <e>
        <p>
          <l>zie</l>
          <r>o<s n="n"/><s n="nt"/><s n="sg"/><s n="loc"/></r>
        </p>
      </e>
      <e>
        <p>
          <l>o</l>
          <r>o<s n="n"/><s n="nt"/><s n="sg"/><s n="voc"/></r>
        </p>
      </e>
      <e>
        <p>
          <l>a</l>
          <r>o<s n="n"/><s n="nt"/><s n="pl"/><s n="nom"/></r>
        </p>
      </e>
      <e>
        <p>
          <l>ów</l>
          <r>o<s n="n"/><s n="nt"/><s n="pl"/><s n="gen"/></r>
        </p>
      </e>
      <e>
        <p>
          <l>om</l>
          <r>o<s n="n"/><s n="nt"/><s n="pl"/><s n="dat"/></r>
        </p>
      </e>
      <e>
        <p>
          <l>a</l>
          <r>o<s n="n"/><s n="nt"/><s n="pl"/><s n="acc"/></r>
        </p>
      </e>
      <e>
        <p>
          <l>ami</l>
          <r>o<s n="n"/><s n="nt"/><s n="pl"/><s n="ins"/></r>
        </p>
      </e>
      <e>
        <p>
          <l>ach</l>
          <r>o<s n="n"/><s n="nt"/><s n="pl"/><s n="loc"/></r>
        </p>
      </e>
      <e>
        <p>
          <l>a</l>
          <r>o<s n="n"/><s n="nt"/><s n="pl"/><s n="voc"/></r>
        </p>
      </e>
    </pardef>

</pardefs>
