<?xml version="1.0" encoding="UTF-8"?>
<pardefs>
     <!-- http://www.wszpwn.pl/wszpwn/index.jsp?place=Lead07&news_cat_id=31&news_id=1200&layout=13&page=text ~~-(e)m, -(e)ś, -(e)śmy, -(e)ście  
            It's possible to say głupiś for 'you are stupid' etc. -->

  <pardef n="być__enc">
    <e>
      <p>
        <l>m</l>
        <r><j/>być<s n="vbser"/><s n="enc"/><s n="p1"/><s n="sg"/></r>
      </p>
    </e>
    <e>
      <p>
        <l>ś</l>
        <r><j/>być<s n="vbser"/><s n="enc"/><s n="p2"/><s n="sg"/></r>
      </p>
    </e>
    <e>
      <p>
        <l>śmy</l>
        <r><j/>być<s n="vbser"/><s n="enc"/><s n="p1"/><s n="pl"/></r>
      </p>
    </e>
    <e>
      <p>
        <l>ście</l>
        <r><j/>być<s n="vbser"/><s n="enc"/><s n="p2"/><s n="pl"/></r>
      </p>
    </e>
  </pardef>
  <pardef n="być__enc2">
    <e>
      <p>
        <l>em</l>
        <r><j/>być<s n="vbser"/><s n="enc"/><s n="p1"/><s n="sg"/></r>
      </p>
    </e>
    <e>
      <p>
        <l>eś</l>
        <r><j/>być<s n="vbser"/><s n="enc"/><s n="p2"/><s n="sg"/></r>
      </p>
    </e>
    <e>
      <p>
        <l>eśmy</l>
        <r><j/>być<s n="vbser"/><s n="enc"/><s n="p1"/><s n="pl"/></r>
      </p>
    </e>
    <e>
      <p>
        <l>eście</l>
        <r><j/>być<s n="vbser"/><s n="enc"/><s n="p2"/><s n="pl"/></r>
      </p>
    </e>
  </pardef>
</pardefs>